miresta
