Metadata-Version: 2.1
Name: miresta
Version: 0.8
Summary: This package performs a subtraction
Home-page: https://pypi.org/project/miresta
Author: Diana Carolina Zapata Zuluaga
Author-email: dianac.zapata@udea.edu.co
License: MIT
Keywords: subtraction
Platform: UNKNOWN
Classifier: Programming Language :: Python :: 3
Classifier: License :: OSI Approved :: MIT License
Classifier: Operating System :: OS Independent
